rnet-2.4.2.dist-info/METADATA
rnet-2.4.2.dist-info/WHEEL
rnet-2.4.2.dist-info/licenses/LICENSE
rnet.libs/libgcc_s-14e858f0.so.1
rnet/__init__.py
rnet/__init__.pyi
rnet/blocking.py
rnet/blocking.pyi
rnet/cookie.py
rnet/cookie.pyi
rnet/exceptions.py
rnet/exceptions.pyi
rnet/header.py
rnet/header.pyi
rnet/impersonate.py
rnet/impersonate.pyi
rnet/py.typed
rnet/rnet.cpython-310-x86_64-linux-gnu.so
rnet-2.4.2.dist-info/RECORD
