Metadata-Version: 2.4
Name: rnet
Version: 2.4.2
Classifier: Programming Language :: Rust
Classifier: Programming Language :: Python :: Implementation :: CPython
Classifier: Programming Language :: Python :: Implementation :: PyPy
Classifier: Programming Language :: Python :: 3.7
Classifier: Programming Language :: Python :: 3.8
Classifier: Programming Language :: Python :: 3.9
Classifier: Programming Language :: Python :: 3.10
Classifier: Programming Language :: Python :: 3.11
Classifier: Programming Language :: Python :: 3.12
Classifier: Programming Language :: Python :: 3.13
Classifier: License :: OSI Approved :: GNU General Public License v3 (GPLv3)
Classifier: Development Status :: 5 - Production/Stable
Classifier: Intended Audience :: Developers
Classifier: Topic :: Software Development :: Libraries :: Python Modules
Classifier: Operating System :: Microsoft :: Windows
Classifier: Operating System :: POSIX
Classifier: Operating System :: Unix
Classifier: Operating System :: MacOS
License-File: LICENSE
Summary: A blazing-fast Python HTTP client with TLS fingerprint
Keywords: http,client,websocket,ja3,ja4
Author-email: 0x676e67 <gngppz@gmail.com>
License: GPL-3.0
Requires-Python: >=3.7
Project-URL: Documentation, https://github.com/0x676e67/rnet/blob/main/rnet.pyi
Project-URL: Homepage, https://github.com/0x676e67/rnet
Project-URL: Repository, https://github.com/0x676e67/rnet
